keyrock_core/__init__.py
keyrock_core/config_loader/__init__.py
keyrock_core/config_loader/config_loader.py
keyrock_core/config_loader/test_config_loader.py
keyrock_core/hash_util/__init__.py
keyrock_core/hash_util/hash_util.py
keyrock_core/hash_util/test_hash_util.py
keyrock_core/json_util/__init__.py
keyrock_core/json_util/diff.py
keyrock_core/json_util/encoders.py
keyrock_core/json_util/json_util.py
keyrock_core/json_util/test_json_util.py
keyrock_core/sql_util/__init__.py
keyrock_core/sql_util/date_util.py
keyrock_core/sql_util/misc_util.py
keyrock_core/sql_util/query_util.py
keyrock_core/sql_util/test_sql_util.py
keyrock_core-2024.2.17.2150.dist-info/METADATA
keyrock_core-2024.2.17.2150.dist-info/WHEEL
keyrock_core-2024.2.17.2150.dist-info/top_level.txt
keyrock_core-2024.2.17.2150.dist-info/RECORD
