Metadata-Version: 2.1
Name: keyrock-core
Version: 2024.2.17.2150
Requires-Dist: marshmallow ==3.20.2
Requires-Dist: pyyaml ==6.0.1
